{
  "version": 2,
  "env": {
    "DIRECTUS_CLOUD_TOKEN": "@production-directus-cloud-token",
    "MY_AWS_ACCESS_BUCKET": "@tapesme-aws-bucket",
    "MY_AWS_ACCESS_REGION": "@tapesme-aws-region",
    "MY_AWS_ACCESS_KEY_ID": "@tapesme-aws-key-id",
    "MY_AWS_SECRET_KEY": "@tapesme-aws-secret"
  },
  "build": {
    "env": {
      "DIRECTUS_CLOUD_TOKEN": "@production-directus-cloud-token",
      "MY_AWS_ACCESS_BUCKET": "@tapesme-aws-bucket",
      "MY_AWS_ACCESS_REGION": "@tapesme-aws-region",
      "MY_AWS_ACCESS_KEY_ID": "@tapesme-aws-key-id",
      "MY_AWS_SECRET_KEY": "@tapesme-aws-secret"
    }
  }
}
